LICENSE
MANIFEST.in
README.md
setup.py
lxmlbind/__init__.py
lxmlbind/api.py
lxmlbind/base.py
lxmlbind/collections.py
lxmlbind/decorators.py
lxmlbind/property.py
lxmlbind/search.py
lxmlbind.egg-info/PKG-INFO
lxmlbind.egg-info/SOURCES.txt
lxmlbind.egg-info/dependency_links.txt
lxmlbind.egg-info/requires.txt
lxmlbind.egg-info/top_level.txt