Metadata-Version: 1.0
Name: lxmlbind
Version: 1.2
Summary: Python LXML object binding.
Home-page: https://github.com/jessemyers/lxmlbind
Author: Jesse Myers
Author-email: jesse@locationlabs.com
License: UNKNOWN
Platform: UNKNOWN
